{
  "archived_page_url": "https://web.archive.org/web/20260207013744/https://www.aljazeera.net/",
  "original_url": "https://www.aljazeera.net/",
  "capture_timestamp": "20260207013744",
  "analysis_time": "2026-07-15T14:04:38.193202",
  "total_resources": 74,
  "resources": [
    {
      "rewritten_url": "/web/20260207013744im_/https://www.aljazeera.net/wp-content/uploads/2026/02/image-1770401585.jpg?resize=570%2C380&quality=80",
      "full_url": "https://web.archive.org/web/20260207013744im_/https://www.aljazeera.net/wp-content/uploads/2026/02/image-1770401585.jpg?resize=570%2C380&quality=80",
      "status_code": 200,
      "memento_datetime": "Fri, 06 Feb 2026 21:03:10 GMT",
      "content_type": "image/jpeg",
      "final_url": "https://web.archive.org/web/20260206210310im_/https://www.aljazeera.net/wp-content/uploads/2026/02/image-1770401585.jpg?quality=80&resize=570%2C380",
      "available": true,
      "delta_text": "- 4 hours, 34 minutes",
      "type": "images"
    },
    {
      "rewritten_url": "/web/20260207013744im_/https://www.aljazeera.net/wp-content/uploads/2026/02/5646-1770417101.png?resize=770%2C513&quality=80",
      "full_url": "https://web.archive.org/web/20260207013744im_/https://www.aljazeera.net/wp-content/uploads/2026/02/5646-1770417101.png?resize=770%2C513&quality=80",
      "status_code": 200,
      "memento_datetime": "Fri, 06 Feb 2026 22:58:38 GMT",
      "content_type": "image/png",
      "final_url": "https://web.archive.org/web/20260206225838im_/https://www.aljazeera.net/wp-content/uploads/2026/02/5646-1770417101.png?quality=80&resize=770%2C513",
      "available": true,
      "delta_text": "- 2 hours, 39 minutes",
      "type": "images"
    },
    {
      "rewritten_url": "/web/20260207013744im_/https://www.aljazeera.net/wp-content/uploads/2026/02/5646-1770417101.png?resize=770%2C513&quality=80",
      "full_url": "https://web.archive.org/web/20260207013744im_/https://www.aljazeera.net/wp-content/uploads/2026/02/5646-1770417101.png?resize=770%2C513&quality=80",
      "status_code": 200,
      "memento_datetime": "Fri, 06 Feb 2026 22:58:38 GMT",
      "content_type": "image/png",
      "final_url": "https://web.archive.org/web/20260206225838im_/https://www.aljazeera.net/wp-content/uploads/2026/02/5646-1770417101.png?quality=80&resize=770%2C513",
      "available": true,
      "delta_text": "- 2 hours, 39 minutes",
      "type": "images"
    },
    {
      "rewritten_url": "/web/20260207013744im_/https://www.aljazeera.net/wp-content/uploads/2026/02/reuters_698679f9-1770420729.jpg?resize=770%2C513&quality=80",
      "full_url": "https://web.archive.org/web/20260207013744im_/https://www.aljazeera.net/wp-content/uploads/2026/02/reuters_698679f9-1770420729.jpg?resize=770%2C513&quality=80",
      "status_code": 200,
      "memento_datetime": "Sat, 07 Feb 2026 01:38:39 GMT",
      "content_type": "image/jpeg",
      "final_url": "https://web.archive.org/web/20260207013839im_/https://www.aljazeera.net/wp-content/uploads/2026/02/reuters_698679f9-1770420729.jpg?resize=770%2C513&quality=80",
      "available": true,
      "delta_text": "+ 55 seconds",
      "type": "images"
    },
    {
      "rewritten_url": "/web/20260207013744im_/https://www.aljazeera.net/wp-content/uploads/2026/02/reuters_698679f9-1770420729.jpg?resize=770%2C513&quality=80",
      "full_url": "https://web.archive.org/web/20260207013744im_/https://www.aljazeera.net/wp-content/uploads/2026/02/reuters_698679f9-1770420729.jpg?resize=770%2C513&quality=80",
      "status_code": 200,
      "memento_datetime": "Sat, 07 Feb 2026 01:38:39 GMT",
      "content_type": "image/jpeg",
      "final_url": "https://web.archive.org/web/20260207013839im_/https://www.aljazeera.net/wp-content/uploads/2026/02/reuters_698679f9-1770420729.jpg?resize=770%2C513&quality=80",
      "available": true,
      "delta_text": "+ 55 seconds",
      "type": "images"
    },
    {
      "rewritten_url": "/web/20260207013744im_/https://www.aljazeera.net/wp-content/uploads/2026/02/ap_698663e74bc6f-1770415079.jpg?resize=770%2C513&quality=80",
      "full_url": "https://web.archive.org/web/20260207013744im_/https://www.aljazeera.net/wp-content/uploads/2026/02/ap_698663e74bc6f-1770415079.jpg?resize=770%2C513&quality=80",
      "status_code": 200,
      "memento_datetime": "Sat, 07 Feb 2026 01:41:13 GMT",
      "content_type": "image/jpeg",
      "final_url": "https://web.archive.org/web/20260207014113im_/https://www.aljazeera.net/wp-content/uploads/2026/02/ap_698663e74bc6f-1770415079.jpg?quality=80&resize=770%2C513",
      "available": true,
      "delta_text": "+ 3 minutes",
      "type": "images"
    },
    {
      "rewritten_url": "/web/20260207013744im_/https://www.aljazeera.net/wp-content/uploads/2026/02/reuters_69863ef7-1770405623.jpg?resize=770%2C513&quality=80",
      "full_url": "https://web.archive.org/web/20260207013744im_/https://www.aljazeera.net/wp-content/uploads/2026/02/reuters_69863ef7-1770405623.jpg?resize=770%2C513&quality=80",
      "status_code": 200,
      "memento_datetime": "Fri, 06 Feb 2026 21:03:10 GMT",
      "content_type": "image/jpeg",
      "final_url": "https://web.archive.org/web/20260206210310im_/https://www.aljazeera.net/wp-content/uploads/2026/02/reuters_69863ef7-1770405623.jpg?resize=770%2C513&quality=80",
      "available": true,
      "delta_text": "- 4 hours, 34 minutes",
      "type": "images"
    },
    {
      "rewritten_url": "/web/20260207013744im_/https://www.aljazeera.net/wp-content/uploads/2026/02/654654-1770396689.png?resize=770%2C513&quality=80",
      "full_url": "https://web.archive.org/web/20260207013744im_/https://www.aljazeera.net/wp-content/uploads/2026/02/654654-1770396689.png?resize=770%2C513&quality=80",
      "status_code": 200,
      "memento_datetime": "Fri, 06 Feb 2026 21:03:35 GMT",
      "content_type": "image/png",
      "final_url": "https://web.archive.org/web/20260206210335im_/https://www.aljazeera.net/wp-content/uploads/2026/02/654654-1770396689.png?resize=770%2C513&quality=80",
      "available": true,
      "delta_text": "- 4 hours, 34 minutes",
      "type": "images"
    },
    {
      "rewritten_url": "/web/20260207013744im_/https://www.aljazeera.net/wp-content/uploads/2025/02/007-1740506803.jpeg?resize=770%2C513&quality=80",
      "full_url": "https://web.archive.org/web/20260207013744im_/https://www.aljazeera.net/wp-content/uploads/2025/02/007-1740506803.jpeg?resize=770%2C513&quality=80",
      "status_code": 200,
      "memento_datetime": "Fri, 06 Feb 2026 21:03:51 GMT",
      "content_type": "image/jpeg",
      "final_url": "https://web.archive.org/web/20260206210351im_/https://www.aljazeera.net/wp-content/uploads/2025/02/007-1740506803.jpeg?resize=770%2C513&quality=80",
      "available": true,
      "delta_text": "- 4 hours, 33 minutes",
      "type": "images"
    },
    {
      "rewritten_url": "/web/20260207013744im_/https://www.aljazeera.net/wp-content/uploads/2026/02/ap_6983aa2cbaf4b-1770236460.jpg?resize=770%2C513&quality=80",
      "full_url": "https://web.archive.org/web/20260207013744im_/https://www.aljazeera.net/wp-content/uploads/2026/02/ap_6983aa2cbaf4b-1770236460.jpg?resize=770%2C513&quality=80",
      "status_code": 200,
      "memento_datetime": "Fri, 06 Feb 2026 21:03:55 GMT",
      "content_type": "image/jpeg",
      "final_url": "https://web.archive.org/web/20260206210355im_/https://www.aljazeera.net/wp-content/uploads/2026/02/ap_6983aa2cbaf4b-1770236460.jpg?resize=770%2C513&quality=80",
      "available": true,
      "delta_text": "- 4 hours, 33 minutes",
      "type": "images"
    },
    {
      "rewritten_url": "/web/20260207013744im_/https://www.aljazeera.net/wp-content/uploads/2025/02/شعيب-1766142923.jpeg?resize=96%2C96&quality=80",
      "full_url": "https://web.archive.org/web/20260207013744im_/https://www.aljazeera.net/wp-content/uploads/2025/02/شعيب-1766142923.jpeg?resize=96%2C96&quality=80",
      "status_code": 200,
      "memento_datetime": "Fri, 06 Feb 2026 22:56:41 GMT",
      "content_type": "image/jpeg",
      "final_url": "https://web.archive.org/web/20260206225641im_/https://www.aljazeera.net/wp-content/uploads/2025/02/%D8%B4%D8%B9%D9%8A%D8%A8-1766142923.jpeg?resize=96%2C96&quality=80",
      "available": true,
      "delta_text": "- 2 hours, 41 minutes",
      "type": "images"
    },
    {
      "rewritten_url": "/web/20260207013744im_/https://www.aljazeera.net/wp-content/uploads/2000/01/24c02a35-f0f0-465c-a0f4-b47abbb8f54f.jpeg?resize=96%2C96&quality=80",
      "full_url": "https://web.archive.org/web/20260207013744im_/https://www.aljazeera.net/wp-content/uploads/2000/01/24c02a35-f0f0-465c-a0f4-b47abbb8f54f.jpeg?resize=96%2C96&quality=80",
      "status_code": 200,
      "memento_datetime": "Fri, 06 Feb 2026 21:19:05 GMT",
      "content_type": "image/jpeg",
      "final_url": "https://web.archive.org/web/20260206211905im_/https://www.aljazeera.net/wp-content/uploads/2000/01/24c02a35-f0f0-465c-a0f4-b47abbb8f54f.jpeg?quality=80&resize=96%2C96",
      "available": true,
      "delta_text": "- 4 hours, 18 minutes",
      "type": "images"
    },
    {
      "rewritten_url": "/web/20260207013744im_/https://www.aljazeera.net/wp-content/uploads/2024/01/ذات-1704650574.jpg?resize=96%2C96&quality=80",
      "full_url": "https://web.archive.org/web/20260207013744im_/https://www.aljazeera.net/wp-content/uploads/2024/01/ذات-1704650574.jpg?resize=96%2C96&quality=80",
      "status_code": 200,
      "memento_datetime": "Fri, 06 Feb 2026 21:03:56 GMT",
      "content_type": "image/jpeg",
      "final_url": "https://web.archive.org/web/20260206210356im_/https://www.aljazeera.net/wp-content/uploads/2024/01/%D8%B0%D8%A7%D8%AA-1704650574.jpg?resize=96%2C96&quality=80",
      "available": true,
      "delta_text": "- 4 hours, 33 minutes",
      "type": "images"
    },
    {
      "rewritten_url": "/web/20260207013744im_/https://www.aljazeera.net/wp-content/uploads/2026/02/حداد-1770283323.png?resize=96%2C96&quality=80",
      "full_url": "https://web.archive.org/web/20260207013744im_/https://www.aljazeera.net/wp-content/uploads/2026/02/حداد-1770283323.png?resize=96%2C96&quality=80",
      "status_code": 200,
      "memento_datetime": "Fri, 06 Feb 2026 21:04:00 GMT",
      "content_type": "image/png",
      "final_url": "https://web.archive.org/web/20260206210400im_/https://www.aljazeera.net/wp-content/uploads/2026/02/%D8%AD%D8%AF%D8%A7%D8%AF-1770283323.png?resize=96%2C96&quality=80",
      "available": true,
      "delta_text": "- 4 hours, 33 minutes",
      "type": "images"
    },
    {
      "rewritten_url": "/web/20260207013744im_/https://www.aljazeera.net/wp-content/uploads/2000/01/36d491fc-fe11-4e65-b050-b93b137440a3-e1739176623170.png?resize=96%2C96&quality=80",
      "full_url": "https://web.archive.org/web/20260207013744im_/https://www.aljazeera.net/wp-content/uploads/2000/01/36d491fc-fe11-4e65-b050-b93b137440a3-e1739176623170.png?resize=96%2C96&quality=80",
      "status_code": 200,
      "memento_datetime": "Fri, 06 Feb 2026 21:04:01 GMT",
      "content_type": "image/png",
      "final_url": "https://web.archive.org/web/20260206210401im_/https://www.aljazeera.net/wp-content/uploads/2000/01/36d491fc-fe11-4e65-b050-b93b137440a3-e1739176623170.png?resize=96%2C96&quality=80",
      "available": true,
      "delta_text": "- 4 hours, 33 minutes",
      "type": "images"
    },
    {
      "rewritten_url": "/web/20260207013744im_/https://www.aljazeera.net/wp-content/uploads/2020/05/ماجد-1732831260.png?resize=96%2C96&quality=80",
      "full_url": "https://web.archive.org/web/20260207013744im_/https://www.aljazeera.net/wp-content/uploads/2020/05/ماجد-1732831260.png?resize=96%2C96&quality=80",
      "status_code": 200,
      "memento_datetime": "Fri, 06 Feb 2026 21:04:01 GMT",
      "content_type": "image/png",
      "final_url": "https://web.archive.org/web/20260206210401im_/https://www.aljazeera.net/wp-content/uploads/2020/05/%D9%85%D8%A7%D8%AC%D8%AF-1732831260.png?resize=96%2C96&quality=80",
      "available": true,
      "delta_text": "- 4 hours, 33 minutes",
      "type": "images"
    },
    {
      "rewritten_url": "/web/20260207013744im_/https://www.aljazeera.net/wp-content/uploads/2026/02/ap_69867bfd944d0-1770421245.jpg?resize=770%2C513&quality=80",
      "full_url": "https://web.archive.org/web/20260207013744im_/https://www.aljazeera.net/wp-content/uploads/2026/02/ap_69867bfd944d0-1770421245.jpg?resize=770%2C513&quality=80",
      "status_code": 200,
      "memento_datetime": "Sat, 07 Feb 2026 01:40:10 GMT",
      "content_type": "image/jpeg",
      "final_url": "https://web.archive.org/web/20260207014010im_/https://www.aljazeera.net/wp-content/uploads/2026/02/ap_69867bfd944d0-1770421245.jpg?quality=80&resize=770%2C513",
      "available": true,
      "delta_text": "+ 2 minutes",
      "type": "images"
    },
    {
      "rewritten_url": "/web/20260207013744im_/https://www.aljazeera.net/wp-content/uploads/2026/01/reuters_696bb831-1768667185.jpg?resize=770%2C513&quality=80",
      "full_url": "https://web.archive.org/web/20260207013744im_/https://www.aljazeera.net/wp-content/uploads/2026/01/reuters_696bb831-1768667185.jpg?resize=770%2C513&quality=80",
      "status_code": 200,
      "memento_datetime": "Fri, 06 Feb 2026 20:32:52 GMT",
      "content_type": "image/jpeg",
      "final_url": "https://web.archive.org/web/20260206203252im_/https://www.aljazeera.net/wp-content/uploads/2026/01/reuters_696bb831-1768667185.jpg?resize=770%2C513&quality=80",
      "available": true,
      "delta_text": "- 5 hours, 4 minutes",
      "type": "images"
    },
    {
      "rewritten_url": "/web/20260207013744im_/https://www.aljazeera.net/wp-content/uploads/2026/02/GettyImages-22453993591-1770408756.jpg?resize=770%2C513&quality=80",
      "full_url": "https://web.archive.org/web/20260207013744im_/https://www.aljazeera.net/wp-content/uploads/2026/02/GettyImages-22453993591-1770408756.jpg?resize=770%2C513&quality=80",
      "status_code": 200,
      "memento_datetime": "Sun, 08 Feb 2026 14:18:14 GMT",
      "content_type": "image/jpeg",
      "final_url": "https://web.archive.org/web/20260208141814im_/https://www.aljazeera.net/wp-content/uploads/2026/02/GettyImages-22453993591-1770408756.jpg?resize=770%2C513&quality=80",
      "available": true,
      "delta_text": "+ 1 day, 12 hours",
      "type": "images"
    },
    {
      "rewritten_url": "/web/20260207013744im_/https://www.aljazeera.net/wp-content/uploads/2026/01/afp_697aad80d549-1769647488.jpg?resize=270%2C180&quality=80",
      "full_url": "https://web.archive.org/web/20260207013744im_/https://www.aljazeera.net/wp-content/uploads/2026/01/afp_697aad80d549-1769647488.jpg?resize=270%2C180&quality=80",
      "status_code": 200,
      "memento_datetime": "Wed, 04 Feb 2026 16:59:27 GMT",
      "content_type": "image/jpeg",
      "final_url": "https://web.archive.org/web/20260204165927im_/https://www.aljazeera.net/wp-content/uploads/2026/01/afp_697aad80d549-1769647488.jpg?resize=270%2C180&quality=80",
      "available": true,
      "delta_text": "- 2 days, 8 hours",
      "type": "images"
    },
    {
      "rewritten_url": "/web/20260207013744im_/https://www.aljazeera.net/wp-content/uploads/2026/02/0605-1770411585.jpg?resize=270%2C180&quality=80",
      "full_url": "https://web.archive.org/web/20260207013744im_/https://www.aljazeera.net/wp-content/uploads/2026/02/0605-1770411585.jpg?resize=270%2C180&quality=80",
      "status_code": 200,
      "memento_datetime": "Sat, 07 Feb 2026 04:56:35 GMT",
      "content_type": "image/jpeg",
      "final_url": "https://web.archive.org/web/20260207045635im_/https://www.aljazeera.net/wp-content/uploads/2026/02/0605-1770411585.jpg?quality=80&resize=270%2C180",
      "available": true,
      "delta_text": "+ 3 hours, 18 minutes",
      "type": "images"
    },
    {
      "rewritten_url": "/web/20260207013744im_/https://www.aljazeera.net/wp-content/uploads/2026/02/reuters_698656c8-1770411720.jpg?resize=270%2C180&quality=80",
      "full_url": "https://web.archive.org/web/20260207013744im_/https://www.aljazeera.net/wp-content/uploads/2026/02/reuters_698656c8-1770411720.jpg?resize=270%2C180&quality=80",
      "status_code": 200,
      "memento_datetime": "Sat, 07 Feb 2026 23:26:09 GMT",
      "content_type": "image/jpeg",
      "final_url": "https://web.archive.org/web/20260207232609im_/https://www.aljazeera.net/wp-content/uploads/2026/02/reuters_698656c8-1770411720.jpg?resize=270%2C180&quality=80",
      "available": true,
      "delta_text": "+ 21 hours, 48 minutes",
      "type": "images"
    },
    {
      "rewritten_url": "/web/20260207013744im_/https://www.aljazeera.net/wp-content/uploads/2026/02/6-1770402765.jpg?resize=270%2C180&quality=80",
      "full_url": "https://web.archive.org/web/20260207013744im_/https://www.aljazeera.net/wp-content/uploads/2026/02/6-1770402765.jpg?resize=270%2C180&quality=80",
      "status_code": 200,
      "memento_datetime": "Fri, 06 Feb 2026 21:04:59 GMT",
      "content_type": "image/jpeg",
      "final_url": "https://web.archive.org/web/20260206210459im_/https://www.aljazeera.net/wp-content/uploads/2026/02/6-1770402765.jpg?resize=270%2C180&quality=80",
      "available": true,
      "delta_text": "- 4 hours, 32 minutes",
      "type": "images"
    },
    {
      "rewritten_url": "/web/20260207013744im_/https://www.aljazeera.net/wp-content/uploads/2025/12/epa_695103f34b61-1766917107.jpg?resize=270%2C180&quality=80",
      "full_url": "https://web.archive.org/web/20260207013744im_/https://www.aljazeera.net/wp-content/uploads/2025/12/epa_695103f34b61-1766917107.jpg?resize=270%2C180&quality=80",
      "status_code": 200,
      "memento_datetime": "Fri, 06 Feb 2026 21:05:10 GMT",
      "content_type": "image/jpeg",
      "final_url": "https://web.archive.org/web/20260206210510im_/https://www.aljazeera.net/wp-content/uploads/2025/12/epa_695103f34b61-1766917107.jpg?resize=270%2C180&quality=80",
      "available": true,
      "delta_text": "- 4 hours, 32 minutes",
      "type": "images"
    },
    {
      "rewritten_url": "/web/20260207013744im_/https://www.aljazeera.net/wp-content/uploads/2025/08/Untitled-3-1754401777.jpg?resize=270%2C180&quality=80",
      "full_url": "https://web.archive.org/web/20260207013744im_/https://www.aljazeera.net/wp-content/uploads/2025/08/Untitled-3-1754401777.jpg?resize=270%2C180&quality=80",
      "status_code": 200,
      "memento_datetime": "Fri, 06 Feb 2026 21:28:26 GMT",
      "content_type": "image/jpeg",
      "final_url": "https://web.archive.org/web/20260206212826im_/https://www.aljazeera.net/wp-content/uploads/2025/08/Untitled-3-1754401777.jpg?resize=270%2C180&quality=80",
      "available": true,
      "delta_text": "- 4 hours, 9 minutes",
      "type": "images"
    },
    {
      "rewritten_url": "/web/20260207013744im_/https://www.aljazeera.net/wp-content/uploads/2026/02/8976453122-1770276433.jpg?resize=270%2C180&quality=80",
      "full_url": "https://web.archive.org/web/20260207013744im_/https://www.aljazeera.net/wp-content/uploads/2026/02/8976453122-1770276433.jpg?resize=270%2C180&quality=80",
      "status_code": 200,
      "memento_datetime": "Fri, 06 Feb 2026 21:04:39 GMT",
      "content_type": "image/jpeg",
      "final_url": "https://web.archive.org/web/20260206210439im_/https://www.aljazeera.net/wp-content/uploads/2026/02/8976453122-1770276433.jpg?quality=80&resize=270%2C180",
      "available": true,
      "delta_text": "- 4 hours, 33 minutes",
      "type": "images"
    },
    {
      "rewritten_url": "/web/20260207013744im_/https://www.aljazeera.net/wp-content/uploads/2025/09/epa_68d8e47d0282-1759044733.jpg?resize=270%2C180&quality=80",
      "full_url": "https://web.archive.org/web/20260207013744im_/https://www.aljazeera.net/wp-content/uploads/2025/09/epa_68d8e47d0282-1759044733.jpg?resize=270%2C180&quality=80",
      "status_code": 200,
      "memento_datetime": "Fri, 06 Feb 2026 21:04:39 GMT",
      "content_type": "image/jpeg",
      "final_url": "https://web.archive.org/web/20260206210439im_/https://www.aljazeera.net/wp-content/uploads/2025/09/epa_68d8e47d0282-1759044733.jpg?quality=80&resize=270%2C180",
      "available": true,
      "delta_text": "- 4 hours, 33 minutes",
      "type": "images"
    },
    {
      "rewritten_url": "/web/20260207013744im_/https://www.aljazeera.net/wp-content/uploads/2025/07/lkl-1-1753084362.jpg?resize=270%2C180&quality=80",
      "full_url": "https://web.archive.org/web/20260207013744im_/https://www.aljazeera.net/wp-content/uploads/2025/07/lkl-1-1753084362.jpg?resize=270%2C180&quality=80",
      "status_code": 200,
      "memento_datetime": "Fri, 06 Feb 2026 22:34:15 GMT",
      "content_type": "image/jpeg",
      "final_url": "https://web.archive.org/web/20260206223415im_/https://www.aljazeera.net/wp-content/uploads/2025/07/lkl-1-1753084362.jpg?resize=270%2C180&quality=80",
      "available": true,
      "delta_text": "- 3 hours, 3 minutes",
      "type": "images"
    },
    {
      "rewritten_url": "/web/20260207013744im_/https://www.aljazeera.net/wp-content/uploads/2026/02/sd6f5s65-1770282541.jpg?resize=270%2C180&quality=80",
      "full_url": "https://web.archive.org/web/20260207013744im_/https://www.aljazeera.net/wp-content/uploads/2026/02/sd6f5s65-1770282541.jpg?resize=270%2C180&quality=80",
      "status_code": 200,
      "memento_datetime": "Fri, 06 Feb 2026 23:11:30 GMT",
      "content_type": "image/jpeg",
      "final_url": "https://web.archive.org/web/20260206231130im_/https://www.aljazeera.net/wp-content/uploads/2026/02/sd6f5s65-1770282541.jpg?resize=270%2C180&quality=80",
      "available": true,
      "delta_text": "- 2 hours, 26 minutes",
      "type": "images"
    },
    {
      "rewritten_url": "/web/20260207013744im_/https://www.aljazeera.net/wp-content/uploads/2026/02/6464-1770396109.png?resize=770%2C513&quality=80",
      "full_url": "https://web.archive.org/web/20260207013744im_/https://www.aljazeera.net/wp-content/uploads/2026/02/6464-1770396109.png?resize=770%2C513&quality=80",
      "status_code": 200,
      "memento_datetime": "Fri, 06 Feb 2026 22:57:15 GMT",
      "content_type": "image/png",
      "final_url": "https://web.archive.org/web/20260206225715im_/https://www.aljazeera.net/wp-content/uploads/2026/02/6464-1770396109.png?resize=770%2C513&quality=80",
      "available": true,
      "delta_text": "- 2 hours, 40 minutes",
      "type": "images"
    },
    {
      "rewritten_url": "/web/20260207013744im_/https://www.aljazeera.net/static/media/blogs-logo.11dca5ab.svg",
      "full_url": "https://web.archive.org/web/20260207013744im_/https://www.aljazeera.net/static/media/blogs-logo.11dca5ab.svg",
      "status_code": 200,
      "memento_datetime": "Fri, 06 Feb 2026 20:45:15 GMT",
      "content_type": "image/svg+xml",
      "final_url": "https://web.archive.org/web/20260206204515im_/https://www.aljazeera.net/static/media/blogs-logo.11dca5ab.svg",
      "available": true,
      "delta_text": "- 4 hours, 52 minutes",
      "type": "images"
    },
    {
      "rewritten_url": "/web/20260207013744im_/https://www.aljazeera.net/wp-content/uploads/2026/02/%D9%A8%D9%A7%D9%A4%D9%A6%D9%A5%D9%A4%D9%A5%D9%A3-1770294837.png?resize=270%2C180&quality=80",
      "full_url": "https://web.archive.org/web/20260207013744im_/https://www.aljazeera.net/wp-content/uploads/2026/02/%D9%A8%D9%A7%D9%A4%D9%A6%D9%A5%D9%A4%D9%A5%D9%A3-1770294837.png?resize=270%2C180&quality=80",
      "status_code": 200,
      "memento_datetime": "Fri, 06 Feb 2026 20:56:31 GMT",
      "content_type": "image/jpeg",
      "final_url": "https://web.archive.org/web/20260206205631im_/https://www.aljazeera.net/wp-content/uploads/2026/02/%D9%A8%D9%A7%D9%A4%D9%A6%D9%A5%D9%A4%D9%A5%D9%A3-1770294837.png?resize=270%2C180&quality=80",
      "available": true,
      "delta_text": "- 4 hours, 41 minutes",
      "type": "images"
    },
    {
      "rewritten_url": "/web/20260207013744im_/https://www.aljazeera.net/static/media/blogs-logo.11dca5ab.svg",
      "full_url": "https://web.archive.org/web/20260207013744im_/https://www.aljazeera.net/static/media/blogs-logo.11dca5ab.svg",
      "status_code": 200,
      "memento_datetime": "Fri, 06 Feb 2026 20:45:15 GMT",
      "content_type": "image/svg+xml",
      "final_url": "https://web.archive.org/web/20260206204515im_/https://www.aljazeera.net/static/media/blogs-logo.11dca5ab.svg",
      "available": true,
      "delta_text": "- 4 hours, 52 minutes",
      "type": "images"
    },
    {
      "rewritten_url": "/web/20260207013744im_/https://www.aljazeera.net/wp-content/uploads/2025/12/Pic-5543-1765576110.jpg?resize=270%2C180&quality=80",
      "full_url": "https://web.archive.org/web/20260207013744im_/https://www.aljazeera.net/wp-content/uploads/2025/12/Pic-5543-1765576110.jpg?resize=270%2C180&quality=80",
      "status_code": 200,
      "memento_datetime": "Fri, 06 Feb 2026 20:46:24 GMT",
      "content_type": "image/jpeg",
      "final_url": "https://web.archive.org/web/20260206204624im_/https://www.aljazeera.net/wp-content/uploads/2025/12/Pic-5543-1765576110.jpg?quality=80&resize=270%2C180",
      "available": true,
      "delta_text": "- 4 hours, 51 minutes",
      "type": "images"
    },
    {
      "rewritten_url": "/web/20260207013744im_/https://www.aljazeera.net/static/media/blogs-logo.11dca5ab.svg",
      "full_url": "https://web.archive.org/web/20260207013744im_/https://www.aljazeera.net/static/media/blogs-logo.11dca5ab.svg",
      "status_code": 200,
      "memento_datetime": "Fri, 06 Feb 2026 20:45:15 GMT",
      "content_type": "image/svg+xml",
      "final_url": "https://web.archive.org/web/20260206204515im_/https://www.aljazeera.net/static/media/blogs-logo.11dca5ab.svg",
      "available": true,
      "delta_text": "- 4 hours, 52 minutes",
      "type": "images"
    },
    {
      "rewritten_url": "/web/20260207013744im_/https://www.aljazeera.net/wp-content/uploads/2026/01/afp_695e4ed014f6-1767788240.jpg?resize=270%2C180&quality=80",
      "full_url": "https://web.archive.org/web/20260207013744im_/https://www.aljazeera.net/wp-content/uploads/2026/01/afp_695e4ed014f6-1767788240.jpg?resize=270%2C180&quality=80",
      "status_code": 200,
      "memento_datetime": "Fri, 06 Feb 2026 20:41:33 GMT",
      "content_type": "image/jpeg",
      "final_url": "https://web.archive.org/web/20260206204133im_/https://www.aljazeera.net/wp-content/uploads/2026/01/afp_695e4ed014f6-1767788240.jpg?resize=270%2C180&quality=80",
      "available": true,
      "delta_text": "- 4 hours, 56 minutes",
      "type": "images"
    },
    {
      "rewritten_url": "/web/20260207013744im_/https://www.aljazeera.net/static/media/blogs-logo.11dca5ab.svg",
      "full_url": "https://web.archive.org/web/20260207013744im_/https://www.aljazeera.net/static/media/blogs-logo.11dca5ab.svg",
      "status_code": 200,
      "memento_datetime": "Fri, 06 Feb 2026 20:45:15 GMT",
      "content_type": "image/svg+xml",
      "final_url": "https://web.archive.org/web/20260206204515im_/https://www.aljazeera.net/static/media/blogs-logo.11dca5ab.svg",
      "available": true,
      "delta_text": "- 4 hours, 52 minutes",
      "type": "images"
    },
    {
      "rewritten_url": "/web/20260207013744im_/https://www.aljazeera.net/wp-content/uploads/2018/09/51051e34-08ec-43de-a3b2-39b34a225506.jpeg?resize=270%2C180&quality=80",
      "full_url": "https://web.archive.org/web/20260207013744im_/https://www.aljazeera.net/wp-content/uploads/2018/09/51051e34-08ec-43de-a3b2-39b34a225506.jpeg?resize=270%2C180&quality=80",
      "status_code": 200,
      "memento_datetime": "Fri, 06 Feb 2026 20:44:53 GMT",
      "content_type": "image/jpeg",
      "final_url": "https://web.archive.org/web/20260206204453im_/https://www.aljazeera.net/wp-content/uploads/2018/09/51051e34-08ec-43de-a3b2-39b34a225506.jpeg?resize=270%2C180&quality=80",
      "available": true,
      "delta_text": "- 4 hours, 52 minutes",
      "type": "images"
    },
    {
      "rewritten_url": "/web/20260207013744im_/https://www.aljazeera.net/static/media/blogs-logo.11dca5ab.svg",
      "full_url": "https://web.archive.org/web/20260207013744im_/https://www.aljazeera.net/static/media/blogs-logo.11dca5ab.svg",
      "status_code": 200,
      "memento_datetime": "Fri, 06 Feb 2026 20:45:15 GMT",
      "content_type": "image/svg+xml",
      "final_url": "https://web.archive.org/web/20260206204515im_/https://www.aljazeera.net/static/media/blogs-logo.11dca5ab.svg",
      "available": true,
      "delta_text": "- 4 hours, 52 minutes",
      "type": "images"
    },
    {
      "rewritten_url": "/web/20260207013744im_/https://www.aljazeera.net/wp-content/uploads/2026/01/Video-4-1769078657.jpg?resize=270%2C180&quality=80",
      "full_url": "https://web.archive.org/web/20260207013744im_/https://www.aljazeera.net/wp-content/uploads/2026/01/Video-4-1769078657.jpg?resize=270%2C180&quality=80",
      "status_code": 200,
      "memento_datetime": "Fri, 06 Feb 2026 20:41:50 GMT",
      "content_type": "image/jpeg",
      "final_url": "https://web.archive.org/web/20260206204150im_/https://www.aljazeera.net/wp-content/uploads/2026/01/Video-4-1769078657.jpg?resize=270%2C180&quality=80",
      "available": true,
      "delta_text": "- 4 hours, 55 minutes",
      "type": "images"
    },
    {
      "rewritten_url": "/web/20260207013744im_/https://www.aljazeera.net/static/media/aj-footer-logo.bac952ad.svg",
      "full_url": "https://web.archive.org/web/20260207013744im_/https://www.aljazeera.net/static/media/aj-footer-logo.bac952ad.svg",
      "status_code": 200,
      "memento_datetime": "Fri, 06 Feb 2026 21:05:20 GMT",
      "content_type": "image/svg+xml",
      "final_url": "https://web.archive.org/web/20260206210520im_/https://www.aljazeera.net/static/media/aj-footer-logo.bac952ad.svg",
      "available": true,
      "delta_text": "- 4 hours, 32 minutes",
      "type": "images"
    },
    {
      "rewritten_url": "https://web.archive.org/web/20260207013744js_/https://cdn.cookielaw.org/scripttemplates/otSDKStub.js",
      "full_url": "https://web.archive.org/web/20260207013744js_/https://cdn.cookielaw.org/scripttemplates/otSDKStub.js",
      "status_code": 200,
      "memento_datetime": "Sat, 07 Feb 2026 01:35:33 GMT",
      "content_type": "application/javascript",
      "final_url": "https://web.archive.org/web/20260207013533js_/https://cdn.cookielaw.org/scripttemplates/otSDKStub.js",
      "available": true,
      "delta_text": "- 2 minutes",
      "type": "scripts"
    },
    {
      "rewritten_url": "/web/20260207013744js_/https://www.aljazeera.net/thirdparty/splunk-otel-web.min.js?v=0.19.1",
      "full_url": "https://web.archive.org/web/20260207013744js_/https://www.aljazeera.net/thirdparty/splunk-otel-web.min.js?v=0.19.1",
      "status_code": 200,
      "memento_datetime": "Fri, 06 Feb 2026 21:05:20 GMT",
      "content_type": "application/javascript; charset=UTF-8",
      "final_url": "https://web.archive.org/web/20260206210520js_/https://www.aljazeera.net/thirdparty/splunk-otel-web.min.js?v=0.19.1",
      "available": true,
      "delta_text": "- 4 hours, 32 minutes",
      "type": "scripts"
    },
    {
      "rewritten_url": "/web/20260207013744js_/https://www.aljazeera.net/thirdparty/ampli.v9.js",
      "full_url": "https://web.archive.org/web/20260207013744js_/https://www.aljazeera.net/thirdparty/ampli.v9.js",
      "status_code": 200,
      "memento_datetime": "Fri, 06 Feb 2026 21:05:20 GMT",
      "content_type": "application/javascript; charset=UTF-8",
      "final_url": "https://web.archive.org/web/20260206210520js_/https://www.aljazeera.net/thirdparty/ampli.v9.js",
      "available": true,
      "delta_text": "- 4 hours, 32 minutes",
      "type": "scripts"
    },
    {
      "rewritten_url": "/web/20260207013744js_/https://www.aljazeera.net/static/js/vendor~common-route~featured-gallery~homepage-route~topic-route~vertical-video-experience~video-rout~7433b1ad.615f86b1.chunk.js",
      "full_url": "https://web.archive.org/web/20260207013744js_/https://www.aljazeera.net/static/js/vendor~common-route~featured-gallery~homepage-route~topic-route~vertical-video-experience~video-rout~7433b1ad.615f86b1.chunk.js",
      "status_code": 200,
      "memento_datetime": "Fri, 06 Feb 2026 21:05:20 GMT",
      "content_type": "application/javascript; charset=UTF-8",
      "final_url": "https://web.archive.org/web/20260206210520js_/https://www.aljazeera.net/static/js/vendor~common-route~featured-gallery~homepage-route~topic-route~vertical-video-experience~video-rout~7433b1ad.615f86b1.chunk.js",
      "available": true,
      "delta_text": "- 4 hours, 32 minutes",
      "type": "scripts"
    },
    {
      "rewritten_url": "/web/20260207013744js_/https://www.aljazeera.net/static/js/component~amp-route~article-route~common-route~gallery-route~homepage-route~liveblog-route~login-rou~d82eadb2.39dc1bbe.chunk.js",
      "full_url": "https://web.archive.org/web/20260207013744js_/https://www.aljazeera.net/static/js/component~amp-route~article-route~common-route~gallery-route~homepage-route~liveblog-route~login-rou~d82eadb2.39dc1bbe.chunk.js",
      "status_code": 200,
      "memento_datetime": "Fri, 06 Feb 2026 21:05:20 GMT",
      "content_type": "application/javascript; charset=UTF-8",
      "final_url": "https://web.archive.org/web/20260206210520js_/https://www.aljazeera.net/static/js/component~amp-route~article-route~common-route~gallery-route~homepage-route~liveblog-route~login-rou~d82eadb2.39dc1bbe.chunk.js",
      "available": true,
      "delta_text": "- 4 hours, 32 minutes",
      "type": "scripts"
    },
    {
      "rewritten_url": "/web/20260207013744js_/https://www.aljazeera.net/static/js/component~common-route~homepage-route~login-route~section-route~topic-route~video-route~6e6dca10.f05f7e1b.chunk.js",
      "full_url": "https://web.archive.org/web/20260207013744js_/https://www.aljazeera.net/static/js/component~common-route~homepage-route~login-route~section-route~topic-route~video-route~6e6dca10.f05f7e1b.chunk.js",
      "status_code": 200,
      "memento_datetime": "Fri, 06 Feb 2026 21:05:20 GMT",
      "content_type": "application/javascript; charset=UTF-8",
      "final_url": "https://web.archive.org/web/20260206210520js_/https://www.aljazeera.net/static/js/component~common-route~homepage-route~login-route~section-route~topic-route~video-route~6e6dca10.f05f7e1b.chunk.js",
      "available": true,
      "delta_text": "- 4 hours, 32 minutes",
      "type": "scripts"
    },
    {
      "rewritten_url": "/web/20260207013744js_/https://www.aljazeera.net/static/js/component~homepage-route~493df0b3.22b45868.chunk.js",
      "full_url": "https://web.archive.org/web/20260207013744js_/https://www.aljazeera.net/static/js/component~homepage-route~493df0b3.22b45868.chunk.js",
      "status_code": 200,
      "memento_datetime": "Fri, 06 Feb 2026 21:05:25 GMT",
      "content_type": "application/javascript; charset=UTF-8",
      "final_url": "https://web.archive.org/web/20260206210525js_/https://www.aljazeera.net/static/js/component~homepage-route~493df0b3.22b45868.chunk.js",
      "available": true,
      "delta_text": "- 4 hours, 32 minutes",
      "type": "scripts"
    },
    {
      "rewritten_url": "/web/20260207013744js_/https://www.aljazeera.net/static/js/component~homepage-route~6e6dca10.30e1a4a6.chunk.js",
      "full_url": "https://web.archive.org/web/20260207013744js_/https://www.aljazeera.net/static/js/component~homepage-route~6e6dca10.30e1a4a6.chunk.js",
      "status_code": 200,
      "memento_datetime": "Fri, 06 Feb 2026 21:05:25 GMT",
      "content_type": "application/javascript; charset=UTF-8",
      "final_url": "https://web.archive.org/web/20260206210525js_/https://www.aljazeera.net/static/js/component~homepage-route~6e6dca10.30e1a4a6.chunk.js",
      "available": true,
      "delta_text": "- 4 hours, 32 minutes",
      "type": "scripts"
    },
    {
      "rewritten_url": "/web/20260207013744js_/https://www.aljazeera.net/static/js/youtube-libs~7dbd8cdd.4e52e52d.chunk.js",
      "full_url": "https://web.archive.org/web/20260207013744js_/https://www.aljazeera.net/static/js/youtube-libs~7dbd8cdd.4e52e52d.chunk.js",
      "status_code": 200,
      "memento_datetime": "Fri, 06 Feb 2026 21:05:25 GMT",
      "content_type": "application/javascript; charset=UTF-8",
      "final_url": "https://web.archive.org/web/20260206210525js_/https://www.aljazeera.net/static/js/youtube-libs~7dbd8cdd.4e52e52d.chunk.js",
      "available": true,
      "delta_text": "- 4 hours, 32 minutes",
      "type": "scripts"
    },
    {
      "rewritten_url": "/web/20260207013744js_/https://www.aljazeera.net/static/js/brightcove-libs~7dbd8cdd.63f20213.chunk.js",
      "full_url": "https://web.archive.org/web/20260207013744js_/https://www.aljazeera.net/static/js/brightcove-libs~7dbd8cdd.63f20213.chunk.js",
      "status_code": 200,
      "memento_datetime": "Fri, 06 Feb 2026 21:05:26 GMT",
      "content_type": "application/javascript; charset=UTF-8",
      "final_url": "https://web.archive.org/web/20260206210526js_/https://www.aljazeera.net/static/js/brightcove-libs~7dbd8cdd.63f20213.chunk.js",
      "available": true,
      "delta_text": "- 4 hours, 32 minutes",
      "type": "scripts"
    },
    {
      "rewritten_url": "/web/20260207013744js_/https://www.aljazeera.net/static/js/amplitude-libs~011b9863.1e50d712.chunk.js",
      "full_url": "https://web.archive.org/web/20260207013744js_/https://www.aljazeera.net/static/js/amplitude-libs~011b9863.1e50d712.chunk.js",
      "status_code": 200,
      "memento_datetime": "Fri, 06 Feb 2026 21:05:26 GMT",
      "content_type": "application/javascript; charset=UTF-8",
      "final_url": "https://web.archive.org/web/20260206210526js_/https://www.aljazeera.net/static/js/amplitude-libs~011b9863.1e50d712.chunk.js",
      "available": true,
      "delta_text": "- 4 hours, 32 minutes",
      "type": "scripts"
    },
    {
      "rewritten_url": "/web/20260207013744js_/https://www.aljazeera.net/static/js/freestar-libs~910c95fb.f1d9178a.chunk.js",
      "full_url": "https://web.archive.org/web/20260207013744js_/https://www.aljazeera.net/static/js/freestar-libs~910c95fb.f1d9178a.chunk.js",
      "status_code": 200,
      "memento_datetime": "Fri, 06 Feb 2026 21:05:26 GMT",
      "content_type": "application/javascript; charset=UTF-8",
      "final_url": "https://web.archive.org/web/20260206210526js_/https://www.aljazeera.net/static/js/freestar-libs~910c95fb.f1d9178a.chunk.js",
      "available": true,
      "delta_text": "- 4 hours, 32 minutes",
      "type": "scripts"
    },
    {
      "rewritten_url": "/web/20260207013744js_/https://www.aljazeera.net/static/js/firebase-packages~7dbd8cdd.45d1935d.chunk.js",
      "full_url": "https://web.archive.org/web/20260207013744js_/https://www.aljazeera.net/static/js/firebase-packages~7dbd8cdd.45d1935d.chunk.js",
      "status_code": 200,
      "memento_datetime": "Fri, 06 Feb 2026 21:05:26 GMT",
      "content_type": "application/javascript; charset=UTF-8",
      "final_url": "https://web.archive.org/web/20260206210526js_/https://www.aljazeera.net/static/js/firebase-packages~7dbd8cdd.45d1935d.chunk.js",
      "available": true,
      "delta_text": "- 4 hours, 32 minutes",
      "type": "scripts"
    },
    {
      "rewritten_url": "/web/20260207013744js_/https://www.aljazeera.net/static/js/react-core~7dbd8cdd.bf8bd5ca.chunk.js",
      "full_url": "https://web.archive.org/web/20260207013744js_/https://www.aljazeera.net/static/js/react-core~7dbd8cdd.bf8bd5ca.chunk.js",
      "status_code": 200,
      "memento_datetime": "Fri, 06 Feb 2026 21:05:26 GMT",
      "content_type": "application/javascript; charset=UTF-8",
      "final_url": "https://web.archive.org/web/20260206210526js_/https://www.aljazeera.net/static/js/react-core~7dbd8cdd.bf8bd5ca.chunk.js",
      "available": true,
      "delta_text": "- 4 hours, 32 minutes",
      "type": "scripts"
    },
    {
      "rewritten_url": "/web/20260207013744js_/https://www.aljazeera.net/static/js/graphql-core~7dbd8cdd.6500d372.chunk.js",
      "full_url": "https://web.archive.org/web/20260207013744js_/https://www.aljazeera.net/static/js/graphql-core~7dbd8cdd.6500d372.chunk.js",
      "status_code": 200,
      "memento_datetime": "Fri, 06 Feb 2026 21:05:26 GMT",
      "content_type": "application/javascript; charset=UTF-8",
      "final_url": "https://web.archive.org/web/20260206210526js_/https://www.aljazeera.net/static/js/graphql-core~7dbd8cdd.6500d372.chunk.js",
      "available": true,
      "delta_text": "- 4 hours, 32 minutes",
      "type": "scripts"
    },
    {
      "rewritten_url": "/web/20260207013744js_/https://www.aljazeera.net/static/js/vendor~main~7dbd8cdd.670b0c65.chunk.js",
      "full_url": "https://web.archive.org/web/20260207013744js_/https://www.aljazeera.net/static/js/vendor~main~7dbd8cdd.670b0c65.chunk.js",
      "status_code": 200,
      "memento_datetime": "Fri, 06 Feb 2026 21:05:26 GMT",
      "content_type": "application/javascript; charset=UTF-8",
      "final_url": "https://web.archive.org/web/20260206210526js_/https://www.aljazeera.net/static/js/vendor~main~7dbd8cdd.670b0c65.chunk.js",
      "available": true,
      "delta_text": "- 4 hours, 32 minutes",
      "type": "scripts"
    },
    {
      "rewritten_url": "/web/20260207013744js_/https://www.aljazeera.net/static/js/vendor~main~e5e84d97.85379177.chunk.js",
      "full_url": "https://web.archive.org/web/20260207013744js_/https://www.aljazeera.net/static/js/vendor~main~e5e84d97.85379177.chunk.js",
      "status_code": 200,
      "memento_datetime": "Fri, 06 Feb 2026 21:05:30 GMT",
      "content_type": "application/javascript; charset=UTF-8",
      "final_url": "https://web.archive.org/web/20260206210530js_/https://www.aljazeera.net/static/js/vendor~main~e5e84d97.85379177.chunk.js",
      "available": true,
      "delta_text": "- 4 hours, 32 minutes",
      "type": "scripts"
    },
    {
      "rewritten_url": "/web/20260207013744js_/https://www.aljazeera.net/static/js/component~main~748942c6.8aa711e6.chunk.js",
      "full_url": "https://web.archive.org/web/20260207013744js_/https://www.aljazeera.net/static/js/component~main~748942c6.8aa711e6.chunk.js",
      "status_code": 200,
      "memento_datetime": "Fri, 06 Feb 2026 21:05:30 GMT",
      "content_type": "application/javascript; charset=UTF-8",
      "final_url": "https://web.archive.org/web/20260206210530js_/https://www.aljazeera.net/static/js/component~main~748942c6.8aa711e6.chunk.js",
      "available": true,
      "delta_text": "- 4 hours, 32 minutes",
      "type": "scripts"
    },
    {
      "rewritten_url": "/web/20260207013744js_/https://www.aljazeera.net/static/js/component~main~b07b7304.01d5f205.chunk.js",
      "full_url": "https://web.archive.org/web/20260207013744js_/https://www.aljazeera.net/static/js/component~main~b07b7304.01d5f205.chunk.js",
      "status_code": 200,
      "memento_datetime": "Fri, 06 Feb 2026 21:05:30 GMT",
      "content_type": "application/javascript; charset=UTF-8",
      "final_url": "https://web.archive.org/web/20260206210530js_/https://www.aljazeera.net/static/js/component~main~b07b7304.01d5f205.chunk.js",
      "available": true,
      "delta_text": "- 4 hours, 32 minutes",
      "type": "scripts"
    },
    {
      "rewritten_url": "/web/20260207013744js_/https://www.aljazeera.net/static/js/component~main~6e6dca10.e619a9e1.chunk.js",
      "full_url": "https://web.archive.org/web/20260207013744js_/https://www.aljazeera.net/static/js/component~main~6e6dca10.e619a9e1.chunk.js",
      "status_code": 200,
      "memento_datetime": "Fri, 06 Feb 2026 21:05:31 GMT",
      "content_type": "application/javascript; charset=UTF-8",
      "final_url": "https://web.archive.org/web/20260206210531js_/https://www.aljazeera.net/static/js/component~main~6e6dca10.e619a9e1.chunk.js",
      "available": true,
      "delta_text": "- 4 hours, 32 minutes",
      "type": "scripts"
    },
    {
      "rewritten_url": "/web/20260207013744js_/https://www.aljazeera.net/static/js/component~main~5db14389.23b8a4c9.chunk.js",
      "full_url": "https://web.archive.org/web/20260207013744js_/https://www.aljazeera.net/static/js/component~main~5db14389.23b8a4c9.chunk.js",
      "status_code": 200,
      "memento_datetime": "Fri, 06 Feb 2026 21:05:31 GMT",
      "content_type": "application/javascript; charset=UTF-8",
      "final_url": "https://web.archive.org/web/20260206210531js_/https://www.aljazeera.net/static/js/component~main~5db14389.23b8a4c9.chunk.js",
      "available": true,
      "delta_text": "- 4 hours, 32 minutes",
      "type": "scripts"
    },
    {
      "rewritten_url": "/web/20260207013744js_/https://www.aljazeera.net/static/js/main.28301129.js",
      "full_url": "https://web.archive.org/web/20260207013744js_/https://www.aljazeera.net/static/js/main.28301129.js",
      "status_code": 200,
      "memento_datetime": "Fri, 06 Feb 2026 21:05:31 GMT",
      "content_type": "application/javascript; charset=UTF-8",
      "final_url": "https://web.archive.org/web/20260206210531js_/https://www.aljazeera.net/static/js/main.28301129.js",
      "available": true,
      "delta_text": "- 4 hours, 32 minutes",
      "type": "scripts"
    },
    {
      "rewritten_url": "/web/20260207013744cs_/https://www.aljazeera.net/static/css/vendor~main~7dbd8cdd.24bf1742.chunk.css",
      "full_url": "https://web.archive.org/web/20260207013744cs_/https://www.aljazeera.net/static/css/vendor~main~7dbd8cdd.24bf1742.chunk.css",
      "status_code": 200,
      "memento_datetime": "Fri, 06 Feb 2026 21:05:36 GMT",
      "content_type": "text/css; charset=UTF-8",
      "final_url": "https://web.archive.org/web/20260206210536cs_/https://www.aljazeera.net/static/css/vendor~main~7dbd8cdd.24bf1742.chunk.css",
      "available": true,
      "delta_text": "- 4 hours, 32 minutes",
      "type": "stylesheets"
    },
    {
      "rewritten_url": "/web/20260207013744cs_/https://www.aljazeera.net/static/css/component~main~748942c6.56c7ad10.chunk.css",
      "full_url": "https://web.archive.org/web/20260207013744cs_/https://www.aljazeera.net/static/css/component~main~748942c6.56c7ad10.chunk.css",
      "status_code": 200,
      "memento_datetime": "Fri, 06 Feb 2026 21:05:36 GMT",
      "content_type": "text/css; charset=UTF-8",
      "final_url": "https://web.archive.org/web/20260206210536cs_/https://www.aljazeera.net/static/css/component~main~748942c6.56c7ad10.chunk.css",
      "available": true,
      "delta_text": "- 4 hours, 32 minutes",
      "type": "stylesheets"
    },
    {
      "rewritten_url": "/web/20260207013744cs_/https://www.aljazeera.net/static/css/component~main~b07b7304.76a41853.chunk.css",
      "full_url": "https://web.archive.org/web/20260207013744cs_/https://www.aljazeera.net/static/css/component~main~b07b7304.76a41853.chunk.css",
      "status_code": 200,
      "memento_datetime": "Fri, 06 Feb 2026 21:05:36 GMT",
      "content_type": "text/css; charset=UTF-8",
      "final_url": "https://web.archive.org/web/20260206210536cs_/https://www.aljazeera.net/static/css/component~main~b07b7304.76a41853.chunk.css",
      "available": true,
      "delta_text": "- 4 hours, 32 minutes",
      "type": "stylesheets"
    },
    {
      "rewritten_url": "/web/20260207013744cs_/https://www.aljazeera.net/static/css/component~main~6e6dca10.9bfb5ad4.chunk.css",
      "full_url": "https://web.archive.org/web/20260207013744cs_/https://www.aljazeera.net/static/css/component~main~6e6dca10.9bfb5ad4.chunk.css",
      "status_code": 200,
      "memento_datetime": "Fri, 06 Feb 2026 21:05:36 GMT",
      "content_type": "text/css; charset=UTF-8",
      "final_url": "https://web.archive.org/web/20260206210536cs_/https://www.aljazeera.net/static/css/component~main~6e6dca10.9bfb5ad4.chunk.css",
      "available": true,
      "delta_text": "- 4 hours, 32 minutes",
      "type": "stylesheets"
    },
    {
      "rewritten_url": "/web/20260207013744cs_/https://www.aljazeera.net/static/css/component~main~5db14389.82209335.chunk.css",
      "full_url": "https://web.archive.org/web/20260207013744cs_/https://www.aljazeera.net/static/css/component~main~5db14389.82209335.chunk.css",
      "status_code": 200,
      "memento_datetime": "Fri, 06 Feb 2026 21:05:36 GMT",
      "content_type": "text/css; charset=UTF-8",
      "final_url": "https://web.archive.org/web/20260206210536cs_/https://www.aljazeera.net/static/css/component~main~5db14389.82209335.chunk.css",
      "available": true,
      "delta_text": "- 4 hours, 32 minutes",
      "type": "stylesheets"
    },
    {
      "rewritten_url": "/web/20260207013744cs_/https://www.aljazeera.net/static/css/vendor~common-route~featured-gallery~homepage-route~topic-route~vertical-video-experience~video-rout~7433b1ad.76106ea4.chunk.css",
      "full_url": "https://web.archive.org/web/20260207013744cs_/https://www.aljazeera.net/static/css/vendor~common-route~featured-gallery~homepage-route~topic-route~vertical-video-experience~video-rout~7433b1ad.76106ea4.chunk.css",
      "status_code": 200,
      "memento_datetime": "Fri, 06 Feb 2026 21:05:36 GMT",
      "content_type": "text/css; charset=UTF-8",
      "final_url": "https://web.archive.org/web/20260206210536cs_/https://www.aljazeera.net/static/css/vendor~common-route~featured-gallery~homepage-route~topic-route~vertical-video-experience~video-rout~7433b1ad.76106ea4.chunk.css",
      "available": true,
      "delta_text": "- 4 hours, 32 minutes",
      "type": "stylesheets"
    },
    {
      "rewritten_url": "/web/20260207013744cs_/https://www.aljazeera.net/static/css/component~amp-route~article-route~common-route~gallery-route~homepage-route~liveblog-route~login-rou~d82eadb2.713efbae.chunk.css",
      "full_url": "https://web.archive.org/web/20260207013744cs_/https://www.aljazeera.net/static/css/component~amp-route~article-route~common-route~gallery-route~homepage-route~liveblog-route~login-rou~d82eadb2.713efbae.chunk.css",
      "status_code": 200,
      "memento_datetime": "Fri, 06 Feb 2026 21:05:35 GMT",
      "content_type": "text/css; charset=UTF-8",
      "final_url": "https://web.archive.org/web/20260206210535cs_/https://www.aljazeera.net/static/css/component~amp-route~article-route~common-route~gallery-route~homepage-route~liveblog-route~login-rou~d82eadb2.713efbae.chunk.css",
      "available": true,
      "delta_text": "- 4 hours, 32 minutes",
      "type": "stylesheets"
    },
    {
      "rewritten_url": "/web/20260207013744cs_/https://www.aljazeera.net/static/css/component~common-route~homepage-route~login-route~section-route~topic-route~video-route~6e6dca10.989bfdba.chunk.css",
      "full_url": "https://web.archive.org/web/20260207013744cs_/https://www.aljazeera.net/static/css/component~common-route~homepage-route~login-route~section-route~topic-route~video-route~6e6dca10.989bfdba.chunk.css",
      "status_code": 200,
      "memento_datetime": "Fri, 06 Feb 2026 21:05:35 GMT",
      "content_type": "text/css; charset=UTF-8",
      "final_url": "https://web.archive.org/web/20260206210535cs_/https://www.aljazeera.net/static/css/component~common-route~homepage-route~login-route~section-route~topic-route~video-route~6e6dca10.989bfdba.chunk.css",
      "available": true,
      "delta_text": "- 4 hours, 32 minutes",
      "type": "stylesheets"
    },
    {
      "rewritten_url": "/web/20260207013744cs_/https://www.aljazeera.net/static/css/component~homepage-route~493df0b3.775423ed.chunk.css",
      "full_url": "https://web.archive.org/web/20260207013744cs_/https://www.aljazeera.net/static/css/component~homepage-route~493df0b3.775423ed.chunk.css",
      "status_code": 200,
      "memento_datetime": "Fri, 06 Feb 2026 21:05:35 GMT",
      "content_type": "text/css; charset=UTF-8",
      "final_url": "https://web.archive.org/web/20260206210535cs_/https://www.aljazeera.net/static/css/component~homepage-route~493df0b3.775423ed.chunk.css",
      "available": true,
      "delta_text": "- 4 hours, 32 minutes",
      "type": "stylesheets"
    },
    {
      "rewritten_url": "/web/20260207013744cs_/https://www.aljazeera.net/static/css/component~homepage-route~6e6dca10.669c3451.chunk.css",
      "full_url": "https://web.archive.org/web/20260207013744cs_/https://www.aljazeera.net/static/css/component~homepage-route~6e6dca10.669c3451.chunk.css",
      "status_code": 200,
      "memento_datetime": "Fri, 06 Feb 2026 21:05:35 GMT",
      "content_type": "text/css; charset=UTF-8",
      "final_url": "https://web.archive.org/web/20260206210535cs_/https://www.aljazeera.net/static/css/component~homepage-route~6e6dca10.669c3451.chunk.css",
      "available": true,
      "delta_text": "- 4 hours, 32 minutes",
      "type": "stylesheets"
    },
    {
      "rewritten_url": "https://web.archive.org/web/20260207013744if_/https://www.googletagmanager.com/ns.html?id=GTM-N6778BQ",
      "full_url": "https://web.archive.org/web/20260207013744if_/https://www.googletagmanager.com/ns.html?id=GTM-N6778BQ",
      "status_code": 200,
      "memento_datetime": "Fri, 06 Feb 2026 19:27:17 GMT",
      "content_type": "text/html; charset=UTF-8",
      "final_url": "https://web.archive.org/web/20260206192717if_/https://www.googletagmanager.com/ns.html?id=GTM-N6778BQ",
      "available": true,
      "delta_text": "- 6 hours, 10 minutes",
      "type": "iframes"
    }
  ],
  "summary": {
    "total": 74,
    "available": 74,
    "status_counts": {
      "200": 74
    },
    "by_type": {
      "images": {
        "total": 41,
        "available": 41
      },
      "scripts": {
        "total": 22,
        "available": 22
      },
      "stylesheets": {
        "total": 10,
        "available": 10
      },
      "iframes": {
        "total": 1,
        "available": 1
      }
    }
  }
}